<?xml version="1.0"?><CONFIG>	<SCREEN>		<OFFX>-1440</OFFX>		<OFFY>0</OFFY>		<FULLSCREEN>1</FULLSCREEN>		<TIMEOUT>90</TIMEOUT>	</SCREEN>	<PROMPTS>		<PROMPT id="snapPic" type="0" time="4"><h1>Look up at the mirror and smile!</h1></PROMPT>		<PROMPT id="drawDone" type="0" time="10"><h1>Look up, Clown!</h1> <p> Apply makeup until you are done.</p><p> Click "FINISH" again to see changes.</p></PROMPT>		<PROMPT id="trackerTip" type="0" time="10"><h1>Can't see your Clown Face?</h1> <p> Sit still for a moment and look straight ahead.</p><p> Make sure your hair is out of your face.</p></PROMPT>		<PROMPT id="picSnapped" type="0" time="7"><h1>Your picture has been taken!</h1><p> Now start painting your face,</p><p> or touch the CAMERA to take another picture.</p></PROMPT>		<PROMPT id="paintTip" type="0" time="10"><h1>To start, choose a color and a tool,</h1><p> touch "UNDO" if you make a mistake.</p></PROMPT>		<PROMPT id="paintTip2" type="0" time="10"><h1>Touch "FINISH" when you are done, </h1><p>look into the mirror to see the clown that you are!</p></PROMPT>		<PROMPT id="timeout" type="1" time="6"><h1>Are you still there?</h1><p>Click OK to continue,</p> <p>or the program will reset in 6 seconds.</p></PROMPT>	</PROMPTS></CONFIG>